ovos_phal_plugin_hotkeys/__init__.py
ovos_phal_plugin_hotkeys/version.py
ovos_phal_plugin_hotkeys/keyboard/__init__.py
ovos_phal_plugin_hotkeys/keyboard/__main__.py
ovos_phal_plugin_hotkeys/keyboard/_canonical_names.py
ovos_phal_plugin_hotkeys/keyboard/_darwinkeyboard.py
ovos_phal_plugin_hotkeys/keyboard/_generic.py
ovos_phal_plugin_hotkeys/keyboard/_keyboard_event.py
ovos_phal_plugin_hotkeys/keyboard/_keyboard_tests.py
ovos_phal_plugin_hotkeys/keyboard/_nixcommon.py
ovos_phal_plugin_hotkeys/keyboard/_nixkeyboard.py
ovos_phal_plugin_hotkeys/keyboard/_winkeyboard.py
ovos_phal_plugin_hotkeys/keyboard/_xk_keysyms.py
ovos_PHAL_plugin_hotkeys-0.1.1.dist-info/LICENSE
ovos_PHAL_plugin_hotkeys-0.1.1.dist-info/METADATA
ovos_PHAL_plugin_hotkeys-0.1.1.dist-info/WHEEL
ovos_PHAL_plugin_hotkeys-0.1.1.dist-info/entry_points.txt
ovos_PHAL_plugin_hotkeys-0.1.1.dist-info/top_level.txt
ovos_PHAL_plugin_hotkeys-0.1.1.dist-info/zip-safe
ovos_PHAL_plugin_hotkeys-0.1.1.dist-info/RECORD
